odoo/addons/datev_import_csv_dtvf/README.rst
odoo/addons/datev_import_csv_dtvf/__init__.py
odoo/addons/datev_import_csv_dtvf/__manifest__.py
odoo/addons/datev_import_csv_dtvf/data/sequence.xml
odoo/addons/datev_import_csv_dtvf/examples/datev_export.csv
odoo/addons/datev_import_csv_dtvf/examples/datev_export_semicolon.csv
odoo/addons/datev_import_csv_dtvf/i18n/datev_import_csv_dtvf.pot
odoo/addons/datev_import_csv_dtvf/models/__init__.py
odoo/addons/datev_import_csv_dtvf/models/account_move_line.py
odoo/addons/datev_import_csv_dtvf/readme/CONTRIBUTORS.md
odoo/addons/datev_import_csv_dtvf/readme/DESCRIPTION.md
odoo/addons/datev_import_csv_dtvf/readme/USAGE.md
odoo/addons/datev_import_csv_dtvf/security/ir.model.access.csv
odoo/addons/datev_import_csv_dtvf/static/description/datev_import_csv_wizard.png
odoo/addons/datev_import_csv_dtvf/static/description/datev_import_csv_wizard_error.png
odoo/addons/datev_import_csv_dtvf/static/description/icon.png
odoo/addons/datev_import_csv_dtvf/static/description/index.html
odoo/addons/datev_import_csv_dtvf/tests/__init__.py
odoo/addons/datev_import_csv_dtvf/tests/test_datev_import_csv_dtvf.py
odoo/addons/datev_import_csv_dtvf/wizard/__init__.py
odoo/addons/datev_import_csv_dtvf/wizard/import_move.py
odoo/addons/datev_import_csv_dtvf/wizard/import_move_view.xml
odoo_addon_datev_import_csv_dtvf-18.0.1.1.0.dist-info/METADATA
odoo_addon_datev_import_csv_dtvf-18.0.1.1.0.dist-info/WHEEL
odoo_addon_datev_import_csv_dtvf-18.0.1.1.0.dist-info/top_level.txt
odoo_addon_datev_import_csv_dtvf-18.0.1.1.0.dist-info/RECORD
