Metadata-Version: 2.1
Name: odoo-addon-datev_import_csv_dtvf
Version: 18.0.1.1.0
Requires-Python: >=3.10
Requires-Dist: chardet
Requires-Dist: odoo==18.0.*
Summary: Import account moves generated by external software
Home-page: https://github.com/OCA/l10n-germany
License: AGPL-3
Author: Odoo Community Association (OCA)
Author-email: support@odoo-community.org
Classifier: Programming Language :: Python
Classifier: Framework :: Odoo
Classifier: Framework :: Odoo :: 18.0
Classifier: License :: OSI Approved :: GNU Affero General Public License v3
